c_pyhfst/__init__.pyx
c_pyhfst/analyzer.pxd
c_pyhfst/analyzer.pyx
c_pyhfst/byte_array.pxd
c_pyhfst/byte_array.pyx
c_pyhfst/common.pxd
c_pyhfst/common.pyx
c_pyhfst/constants.h
c_pyhfst/flag_diacritic_operation.pxd
c_pyhfst/flag_diacritic_operation.pyx
c_pyhfst/flag_diacritic_operator.pxd
c_pyhfst/flag_diacritic_operator.pyx
c_pyhfst/transducer.pxd
c_pyhfst/transducer.pyx
c_pyhfst/transducer_alphabet.pxd
c_pyhfst/transducer_alphabet.pyx
c_pyhfst/transducer_header.pxd
c_pyhfst/transducer_header.pyx
pyhfst/__init__.py
pyhfst/analyzer.py
pyhfst/byte_array.py
pyhfst/common.py
pyhfst/flag_diacritic_operation.py
pyhfst/transducer.py
pyhfst/transducer_alphabet.py
pyhfst/transducer_header.py
pyhfst-1.4.0.dist-info/licenses/LICENCE
pyhfst-1.4.0.dist-info/METADATA
pyhfst-1.4.0.dist-info/WHEEL
pyhfst-1.4.0.dist-info/top_level.txt
pyhfst-1.4.0.dist-info/RECORD
