Metadata-Version: 2.4
Name: pyhfst
Version: 1.4.0
Summary: A pure Python implementation of HFST for using HFST optimized lookup transducers (with or without weights)
Home-page: https://github.com/Rootroo-ltd/pyhfst
Author: Khalid Alnajjar and Mika Hämäläinen
Author-email: hello@rootroo.com
License: Apache-2.0
Project-URL: Bug Reports, https://github.com/Rootroo-ltd/pyhfst/issues
Project-URL: Developer, https://rootroo.com/
Keywords: hfst,fst,optimized lookup,hfstol,transducers
Classifier: Development Status :: 5 - Production/Stable
Classifier: Intended Audience :: Developers
Classifier: Topic :: Text Processing :: Linguistic
Classifier: Programming Language :: Python :: 3
License-File: LICENCE
Dynamic: author
Dynamic: author-email
Dynamic: classifier
Dynamic: description
Dynamic: description-content-type
Dynamic: home-page
Dynamic: keywords
Dynamic: license
Dynamic: license-file
Dynamic: project-url
Dynamic: summary
